endpoint_filter/__init__.py
endpoint_filter/main.py
endpoint_filter-0.1.3.dist-info/LICENSE
endpoint_filter-0.1.3.dist-info/METADATA
endpoint_filter-0.1.3.dist-info/WHEEL
endpoint_filter-0.1.3.dist-info/RECORD
